idea/__init__.py
idea/base.py
idea/lite.py
idea/valid.py
idea_format-0.1.15.dist-info/LICENSE
idea_format-0.1.15.dist-info/METADATA
idea_format-0.1.15.dist-info/WHEEL
idea_format-0.1.15.dist-info/top_level.txt
idea_format-0.1.15.dist-info/zip-safe
idea_format-0.1.15.dist-info/RECORD
