Metadata-Version: 2.1
Name: idea-format
Version: 0.1.15
Summary: Python library for working with IDEA messages.
Home-page: https://pypi.org/project/idea-format/
Author: Pavel Kacha
Author-email: pavel.kacha@cesnet.cz
License: ISC
Project-URL: Documentation, https://709.gitlab-pages.cesnet.cz/warden/idea/master/html/manual.html
Project-URL: Source, https://gitlab.cesnet.cz/709/warden/idea
Project-URL: Tracker, https://gitlab.cesnet.cz/709/warden/idea/-/issues
Keywords: library
Classifier: Development Status :: 4 - Beta
Classifier: License :: OSI Approved :: ISC License (ISCL)
Classifier: Programming Language :: Python
License-File: LICENSE
Requires-Dist: ipranges
Requires-Dist: typedcols
